pandabet/__init__.py
pybet/__init__.py
tests/__init__.py
tests/test_pandabet.py
pandabet-0.1.2.dist-info/METADATA
pandabet-0.1.2.dist-info/WHEEL
pandabet-0.1.2.dist-info/top_level.txt
pandabet-0.1.2.dist-info/RECORD
