Metadata-Version: 2.4
Name: pandabet
Version: 0.1.2
Requires-Dist: pandas>=1.0.0
Dynamic: description
Dynamic: description-content-type
Dynamic: requires-dist
